setup.py
ds_udacity_ml_js/Binomialdistribution.py
ds_udacity_ml_js/Gaussiandistribution.py
ds_udacity_ml_js/Generaldistribution.py
ds_udacity_ml_js/__init__.py
ds_udacity_ml_js.egg-info/PKG-INFO
ds_udacity_ml_js.egg-info/SOURCES.txt
ds_udacity_ml_js.egg-info/dependency_links.txt
ds_udacity_ml_js.egg-info/not-zip-safe
ds_udacity_ml_js.egg-info/top_level.txt